odoo/addons/l10n_cl_toponym/README.rst
odoo/addons/l10n_cl_toponym/__init__.py
odoo/addons/l10n_cl_toponym/__manifest__.py
odoo/addons/l10n_cl_toponym/data/res_city.xml
odoo/addons/l10n_cl_toponym/data/res_country.xml
odoo/addons/l10n_cl_toponym/data/res_country_state.xml
odoo/addons/l10n_cl_toponym/data/res_country_state_region.xml
odoo/addons/l10n_cl_toponym/i18n/es.po
odoo/addons/l10n_cl_toponym/i18n/es_CL.po
odoo/addons/l10n_cl_toponym/i18n/l10n_cl_toponym.pot
odoo/addons/l10n_cl_toponym/models/__init__.py
odoo/addons/l10n_cl_toponym/models/res_city.py
odoo/addons/l10n_cl_toponym/models/res_company.py
odoo/addons/l10n_cl_toponym/models/res_country.py
odoo/addons/l10n_cl_toponym/models/res_country_state.py
odoo/addons/l10n_cl_toponym/models/res_country_state_region.py
odoo/addons/l10n_cl_toponym/models/res_partner.py
odoo/addons/l10n_cl_toponym/readme/CONTRIBUTORS.rst
odoo/addons/l10n_cl_toponym/readme/DESCRIPTION.rst
odoo/addons/l10n_cl_toponym/readme/USAGE.rst
odoo/addons/l10n_cl_toponym/security/ir.model.access.csv
odoo/addons/l10n_cl_toponym/security/res_groups.xml
odoo/addons/l10n_cl_toponym/static/description/icon.png
odoo/addons/l10n_cl_toponym/static/description/index.html
odoo/addons/l10n_cl_toponym/static/description/pic1.png
odoo/addons/l10n_cl_toponym/static/description/pic2.png
odoo/addons/l10n_cl_toponym/views/res_city.xml
odoo/addons/l10n_cl_toponym/views/res_company.xml
odoo/addons/l10n_cl_toponym/views/res_country.xml
odoo/addons/l10n_cl_toponym/views/res_country_state.xml
odoo/addons/l10n_cl_toponym/views/res_country_state_region.xml
odoo/addons/l10n_cl_toponym/views/res_partner.xml
odoo12_addon_l10n_cl_toponym-12.0.1.3.1.dist-info/METADATA
odoo12_addon_l10n_cl_toponym-12.0.1.3.1.dist-info/WHEEL
odoo12_addon_l10n_cl_toponym-12.0.1.3.1.dist-info/top_level.txt
odoo12_addon_l10n_cl_toponym-12.0.1.3.1.dist-info/RECORD
