Metadata-Version: 2.1
Name: odoo12-addon-l10n-cl-toponym
Version: 12.0.1.3.1
Summary: Cities, States and Regions of Chile
Home-page: https://github.com/OCA/l10n-chile
Author: Konos, Blanco Martín & Asociados, CubicERP, Open source Integrators, Odoo Community Association (OCA)
Author-email: support@odoo-community.org
License: AGPL-3
Platform: UNKNOWN
Classifier: Programming Language :: Python
Classifier: Framework :: Odoo
Classifier: License :: OSI Approved :: GNU Affero General Public License v3
Classifier: Development Status :: 4 - Beta
Requires-Python: >=3.5
Requires-Dist: odoo (<12.1dev,>=12.0a)
